MANIFEST.in
README.rst
setup.py
bin/roacd
examples/centos/README.rst
examples/centos/roac.cfg
examples/centos/roacd
examples/centos/roacd.conf
examples/centos/roacd_root.conf
examples/scripts/memory.sh
examples/scripts/users.sh
roac/__init__.py
roac/app.py
roac/config.py
roac/functionlist.py
roac/logs.py
roac/matchers.py
roac/result.py
roac/script.py
roac/script_handler.py
roac/timer.py
roac.egg-info/PKG-INFO
roac.egg-info/SOURCES.txt
roac.egg-info/dependency_links.txt
roac.egg-info/not-zip-safe
roac.egg-info/top_level.txt
roac/extra/__init__.py
roac/extra/http_poster.py