Metadata-Version: 1.1
Name: roac
Version: 0.0.1
Summary: System monitoring agent framework
Home-page: https://github.com/roac-monitoring/roac-agent
Author: Javier Aravena Claramunt
Author-email: javier@aravenas.com
License: BSD
Platform: UNKNOWN
Classifier: Development Status :: 2 - Pre-Alpha
Classifier: Intended Audience :: Developers
Classifier: Intended Audience :: System Administrators
Classifier: License :: OSI Approved :: BSD License
Classifier: Operating System :: POSIX
Classifier: Topic :: Software Development :: Libraries :: Application Frameworks
Classifier: Topic :: System :: Monitoring
